Workbook

Sheet 00_使用说明
A1: 「鸭绿江·1950」红色文旅城一期 —— 客流与收入测算模型
A4: ■ 使用方法
A5: 1. 只需修改「01_假设」中黄色底色的单元格(客流、票价、转化率、人均消费、成本、投资等参数);
A6: 2. 「02_收入测算」「03_成本与利润」「04_月度客流」「05_敏感性」全部由公式联动,自动重算;
A7: 3. 三列并行呈现保守/基准/乐观三个客流情景,便于对比;
A9: ■ 模型口径
A10: · 测算年份口径为「稳定运营年」(开业第3年);开业首年建议按基准情景×70%爬坡系数理解;
A11: · 本模型为概念阶段测算(精度±30%),用于投资决策的方向性判断,非施工图预算;
A12: · 收入按一期业态口径(日场演艺/小剧场/餐饮商业/文创/研学/其他),夜演大剧场与酒店属二期,未计入;
A13: · 餐饮商业收入指小镇获得的租金+流水抽成口径,非商户流水;
A15: ■ 关键锚点(外部参照)
A16: · 遵义1935街区(免门票):单月客流120万人次(2025年7月);
... A18: · 丹东2025年春节假期全市客流424万人次,断桥景区2026年元旦客流同比+102%。

Sheet 01_假设
A1: 01 假设参数(黄色单元格可修改)
A3: A. 年客流情景(人次/年) | B3: 保守 | C3: 基准 | D3: 乐观 | E3: 说明
A4: 稳定年入园客流 | B4: 600000 | C4: 1000000 | D4: 1500000 | E4: 基准=城市旗舰锚定率约15%口径;对标遵义1935单月120万的1/14强度
A6: B. 转化率与价格 | B6: 数值 | E6: 说明
A7: 日场《抢渡鸭绿江》观演转化率 | B7: 0.35 | E7: 入园客流中购票观演比例
A8: 日场票价(元/人) | B8: 80 | E8: 对标同类实景演艺80–128元区间下沿
A9: 小剧场观演转化率 | B9: 0.25 | E9: 多剧场轮演,通票含1场后加购
A10: 小剧场平均票价(元/人) | B10: 40 | E10: 单场30–50元
A11: 研学客群占比 | B11: 0.06 | E11: 研学人次占总客流比例
A12: 研学课程客单价(元/人) | B12: 150 | E12: 半日课程口径
A13: 餐饮商业人均贡献(元/人) | B13: 18 | E13: 小镇租金+流水抽成口径(约合商户流水的20%)
A14: 文创零售人均贡献(元/人) | B14: 8 | E14: 自营+联营毛贡献
A15: 停车交通及其他人均(元/人) | B15: 4
A17: C. 成本参数 | B17: 数值 | E17: 说明
A18: 年固定成本(万元) | B18: 4400 | E18: 演职员+运营团队薪酬、物业能耗基础值、管理费用
A19: 变动成本率(占收入) | B19: 0.15 | E19: 随客流变动的耗材、能耗增量、佣金渠道费等
A21: D. 投资参数 | B21: 数值 | E21: 说明
A22: 一期总投资(万元) | B22: 31000 | E22: 详见报告投资估算表;概念级估算±30%

Sheet 02_收入测算
A1: 02 收入测算(万元/年,稳定年)
A3: 收入科目 | B3: 保守 | C3: 基准 | D3: 乐观 | E3: 公式口径
A4: 日场《抢渡鸭绿江》演艺 | B4: ='01_假设'!$B$4*'01_假设'!$B$7*'01_假设'!$B$8/10000 -> 1680 | C4: ='01_假设'!$C$4*'01_假设'!$B$7*'01_假设'!$B$8/10000 -> 2800 | D4: ='01_假设'!$D$4*'01_假设'!$B$7*'01_假设'!$B$8/10000 -> 4200 | E4: 客流×观演转化率×票价
A5: 小剧场群 | B5: ='01_假设'!$B$4*'01_假设'!$B$9*'01_假设'!$B$10/10000 -> 600 | C5: ='01_假设'!$C$4*'01_假设'!$B$9*'01_假设'!$B$10/10000 -> 1000 | D5: ='01_假设'!$D$4*'01_假设'!$B$9*'01_假设'!$B$10/10000 -> 1500 | E5: 客流×转化率×均价
A6: 餐饮商业(租金+抽成) | B6: ='01_假设'!$B$4*'01_假设'!$B$13/10000 -> 1080 | C6: ='01_假设'!$C$4*'01_假设'!$B$13/10000 -> 1800 | D6: ='01_假设'!$D$4*'01_假设'!$B$13/10000 -> 2700 | E6: 客流×人均贡献
A7: 文创零售 | B7: ='01_假设'!$B$4*'01_假设'!$B$14/10000 -> 480 | C7: ='01_假设'!$C$4*'01_假设'!$B$14/10000 -> 800 | D7: ='01_假设'!$D$4*'01_假设'!$B$14/10000 -> 1200 | E7: 客流×人均贡献
A8: 研学课程 | B8: ='01_假设'!$B$4*'01_假设'!$B$11*'01_假设'!$B$12/10000 -> 540 | C8: ='01_假设'!$C$4*'01_假设'!$B$11*'01_假设'!$B$12/10000 -> 900 | D8: ='01_假设'!$D$4*'01_假设'!$B$11*'01_假设'!$B$12/10000 -> 1350 | E8: 客流×研学占比×客单价
A9: 停车交通及其他 | B9: ='01_假设'!$B$4*'01_假设'!$B$15/10000 -> 240 | C9: ='01_假设'!$C$4*'01_假设'!$B$15/10000 -> 400 | D9: ='01_假设'!$D$4*'01_假设'!$B$15/10000 -> 600 | E9: 客流×人均
A10: 收入合计 | B10: =SUM(B4:B9) -> 4620 | C10: =SUM(C4:C9) -> 7700 | D10: =SUM(D4:D9) -> 11550
A11: 人均综合收入(元/人次) | B11: =B10*10000/'01_假设'!$B$4 -> 77 | C11: =C10*10000/'01_假设'!$C$4 -> 77 | D11: =D10*10000/'01_假设'!$D$4 -> 77 | E11: 收入合计÷客流

Sheet 03_成本与利润
A1: 03 成本与利润(万元/年,稳定年)
A3: 科目 | B3: 保守 | C3: 基准 | D3: 乐观 | E3: 公式口径
A4: 收入合计 | B4: ='02_收入测算'!B10 -> 4620 | C4: ='02_收入测算'!C10 -> 7700 | D4: ='02_收入测算'!D10 -> 11550 | E4: 引自02表
A5: 变动成本 | B5: ='02_收入测算'!B10*'01_假设'!$B$19 -> 693 | C5: ='02_收入测算'!C10*'01_假设'!$B$19 -> 1155 | D5: ='02_收入测算'!D10*'01_假设'!$B$19 -> 1732.5 | E5: 收入×变动成本率
A6: 固定成本 | B6: ='01_假设'!$B$18 -> 4400 | C6: ='01_假设'!$B$18 -> 4400 | D6: ='01_假设'!$B$18 -> 4400 | E6: 演职员/运营/物业/管理
A7: EBITDA | B7: =B4-B5-B6 -> -473 | C7: =C4-C5-C6 -> 2145 | D7: =D4-D5-D6 -> 5417.5 | E7: 收入-变动-固定
A8: EBITDA率 | B8: =B7/B4 -> -0.1024 | C8: =C7/C4 -> 0.2786 | D8: =D7/D4 -> 0.469
A9: 一期投资回收期(年) | B9: =IF(B7<=0,"—",'01_假设'!$B$22/B7) -> — | C9: =IF(C7<=0,"—",'01_假设'!$B$22/C7) -> 14.4522 | D9: =IF(D7<=0,"—",'01_假设'!$B$22/D7) -> 5.7222 | E9: 总投资÷EBITDA(简单口径,未计二期与土地增值);EBITDA为负显示「—」
A11: 盈亏平衡客流(万人次/年) | B11: ='01_假设'!$B$18*10000/('02_收入测算'!C11*(1-'01_假设'!$B$19))/10000 -> 67.23 | E11: 固定成本÷人均边际贡献(按基准情景人均收入)

Sheet 04_月度客流
A1: 04 月度客流分布(基准情景)
A3: 月份 | B3: 1月 | C3: 2月 | D3: 3月 | E3: 4月 | F3: 5月 | G3: 6月 | H3: 7月 | I3: 8月 | J3: 9月 | K3: 10月 | L3: 11月 | M3: 12月 | N3: 合计
A4: 占比(可改) | B4: 0.04 | C4: 0.06 | D4: 0.05 | E4: 0.07 | F4: 0.1 | G4: 0.1 | H4: 0.14 | I4: 0.14 | J4: 0.1 | K4: 0.1 | L4: 0.05 | M4: 0.05 | N4: =SUM(B4:M4) -> 1
A5: 客流(万人次) | B5: ='01_假设'!$C$4*B4/10000 -> 4 | C5: ='01_假设'!$C$4*C4/10000 -> 6 | D5: ='01_假设'!$C$4*D4/10000 -> 5 | E5: ='01_假设'!$C$4*E4/10000 -> 7 | F5: ='01_假设'!$C$4*F4/10000 -> 10 | G5: ='01_假设'!$C$4*G4/10000 -> 10 | H5: ='01_假设'!$C$4*H4/10000 -> 14 | I5: ='01_假设'!$C$4*I4/10000 -> 14 | ... M5: ='01_假设'!$C$4*M4/10000 -> 5 | N5: =SUM(B5:M5) -> 100
A7: 日均(万人次/日) | B7: =B5/31 -> 0.13 | C7: =C5/28 -> 0.21 | D7: =D5/31 -> 0.16 | E7: =E5/30 -> 0.23 | F7: =F5/31 -> 0.32 | G7: =G5/30 -> 0.33 | H7: =H5/31 -> 0.45 | I7: =I5/31 -> 0.45 | J7: =J5/30 -> 0.33 | K7: =K5/31 -> 0.32 | L7: =L5/30 -> 0.17 | M7: =M5/31 -> 0.16
A9: 说明:7–8月暑期与5/10月假期为高峰;冬季(11–2月)靠室内小剧场+温泉+「1950年的冬天」主题支撑,占比20%。

Sheet 05_敏感性
A1: 05 敏感性分析:EBITDA(万元)
A3: 客流(万人次)↓ / 人均综合收入(元)→ | B3: 60 | C3: 77 | D3: 95
A4: 60 | B4: =$A4*B$3*(1-'01_假设'!$B$19)-'01_假设'!$B$18 -> -1340 | C4: =$A4*C$3*(1-'01_假设'!$B$19)-'01_假设'!$B$18 -> -473 | D4: =$A4*D$3*(1-'01_假设'!$B$19)-'01_假设'!$B$18 -> 445
A5: 80 | B5: =$A5*B$3*(1-'01_假设'!$B$19)-'01_假设'!$B$18 -> -320 | C5: =$A5*C$3*(1-'01_假设'!$B$19)-'01_假设'!$B$18 -> 836 | D5: =$A5*D$3*(1-'01_假设'!$B$19)-'01_假设'!$B$18 -> 2060
A6: 100 | B6: =$A6*B$3*(1-'01_假设'!$B$19)-'01_假设'!$B$18 -> 700 | C6: =$A6*C$3*(1-'01_假设'!$B$19)-'01_假设'!$B$18 -> 2145 | D6: =$A6*D$3*(1-'01_假设'!$B$19)-'01_假设'!$B$18 -> 3675
A7: 120 | B7: =$A7*B$3*(1-'01_假设'!$B$19)-'01_假设'!$B$18 -> 1720 | C7: =$A7*C$3*(1-'01_假设'!$B$19)-'01_假设'!$B$18 -> 3454 | D7: =$A7*D$3*(1-'01_假设'!$B$19)-'01_假设'!$B$18 -> 5290
A8: 150 | B8: =$A8*B$3*(1-'01_假设'!$B$19)-'01_假设'!$B$18 -> 3250 | C8: =$A8*C$3*(1-'01_假设'!$B$19)-'01_假设'!$B$18 -> 5418 | D8: =$A8*D$3*(1-'01_假设'!$B$19)-'01_假设'!$B$18 -> 7712
A10: 读法:行=年客流,列=人均综合收入;绿色区间为正EBITDA。基准点(100万×77元)EBITDA约2,145万元。
